README.md
setup.py
wapp
wappalyze/Wappalyze.py
wappalyze/__init__.py
wappalyze/__main__.py
wappalyze/apps.json
wappalyze.egg-info/PKG-INFO
wappalyze.egg-info/SOURCES.txt
wappalyze.egg-info/dependency_links.txt
wappalyze.egg-info/requires.txt
wappalyze.egg-info/top_level.txt