Metadata-Version: 2.1
Name: wappalyze
Version: 1.6
Summary: Framework Identifier tool
Home-page: https://github.com/shaddygarg/framework-identifier
Author: Shaddy Garg
Author-email: shaddygarg1@gmail.com
License: UNKNOWN
Platform: UNKNOWN
Classifier: Programming Language :: Python :: 3
Classifier: License :: OSI Approved :: MIT License
Classifier: Operating System :: OS Independent
